<chips>
	<chip name="Miriam-Big-1.5mm">
		<chipWidth>33000</chipWidth>
		<chipHeight>8847</chipHeight>
		<windowWidth>1500.0</windowWidth>
		<windowHeight>1500.0</windowHeight>
		<gapWidth>600.0</gapWidth>
		<gapHeight>600.0</gapHeight>
		<horizontalPitch>50</horizontalPitch>
		<verticalPitch>43.3012701892</verticalPitch>
		<topLeftLinear>15113.4</topLeftLinear>
		<topLeftY>-3744.9375</topLeftY>
		<numHorizontalWindows>16</numHorizontalWindows>
		<triangular>1</triangular>
	</chip>
	<chip name="Miriam-Small-1.1mm">
		<chipWidth>33000</chipWidth>
		<chipHeight>8847</chipHeight>
		<windowWidth>1100.0</windowWidth>
		<windowHeight>1100.0</windowHeight>
		<gapWidth>500.0</gapWidth>
		<gapHeight>500.0</gapHeight>
		<horizontalPitch>50</horizontalPitch>
		<verticalPitch>43.3012701892</verticalPitch>
		<topLeftLinear>14667.0</topLeftLinear>
		<topLeftY>-3602.703125</topLeftY>
		<numHorizontalWindows>21</numHorizontalWindows>
		<triangular>1</triangular>
	</chip>
	<chip name="Finnlitho-old">
		<chipWidth>28618</chipWidth>
		<chipHeight>7784</chipHeight>
		<windowWidth>1200.0</windowWidth>
		<windowHeight>1256.7</windowHeight>
		<gapWidth>530.0</gapWidth>
		<gapHeight>343.3</gapHeight>
		<horizontalPitch>25</horizontalPitch>
		<verticalPitch>21.75</verticalPitch>
		<topLeftLinear>14227.95</topLeftLinear>
		<topLeftY>-3017.5390625</topLeftY>
		<numHorizontalWindows>18</numHorizontalWindows>
		<triangular>1</triangular>
	</chip>
	<chip name="Nadia">
		<chipWidth>27000</chipWidth>
		<chipHeight>10292</chipHeight>
		<windowWidth>27000.0</windowWidth>
		<windowHeight>10292.0</windowHeight>
		<gapWidth>0.0</gapWidth>
		<gapHeight>0.0</gapHeight>
		<horizontalPitch>25</horizontalPitch>
		<verticalPitch>25</verticalPitch>
		<topLeftLinear>9975</topLeftLinear>
		<topLeftY>-6000</topLeftY>
		<numHorizontalWindows>1</numHorizontalWindows>
		<triangular>1</triangular>
	</chip>
	<chip name="2018-Miriam-8-Windows">
		<chipWidth>32720</chipWidth>
		<chipHeight>9186</chipHeight>
		<windowWidth>7580.0</windowWidth>
		<windowHeight>4313.0</windowHeight>
		<gapWidth>800.0</gapWidth>
		<gapHeight>560.0</gapHeight>
		<horizontalPitch>99.98</horizontalPitch>
		<verticalPitch>90.25</verticalPitch>
		<topLeftLinear>4100.0</topLeftLinear>
		<topLeftY>-4600.0</topLeftY>
		<numHorizontalWindows>4</numHorizontalWindows>
		<triangular>1</triangular>
	</chip>
	<chip name="2018-Miriam-8-Windows-hack">
		<chipWidth>24340</chipWidth>
		<chipHeight>9186</chipHeight>
		<windowWidth>7580.0</windowWidth>
		<windowHeight>4313.0</windowHeight>
		<gapWidth>800.0</gapWidth>
		<gapHeight>560.0</gapHeight>
		<horizontalPitch>99.99</horizontalPitch>
		<verticalPitch>90.16</verticalPitch>
		<topLeftLinear>4100.0</topLeftLinear>
		<topLeftY>-4600.0</topLeftY>
		<numHorizontalWindows>3</numHorizontalWindows>
		<triangular>1</triangular>
	</chip>
	<chip name="2018-Miriam-12-Windows">
		<chipWidth>32800</chipWidth>
		<chipHeight>9186</chipHeight>
		<windowWidth>4850.0</windowWidth>
		<windowHeight>4565.0</windowHeight>
		<gapWidth>710.0</gapWidth>
		<gapHeight>560.0</gapHeight>
		<horizontalPitch>99.98</horizontalPitch>
		<verticalPitch>90.18</verticalPitch>
		<topLeftLinear>7269.2</topLeftLinear>
		<topLeftY>-2194.921875</topLeftY>
		<numHorizontalWindows>6</numHorizontalWindows>
		<triangular>1</triangular>
	</chip>
	<chip name="Crater-Chips">
		<chipWidth>32750</chipWidth>
		<chipHeight>10600</chipHeight>
		<windowWidth>10000.0</windowWidth>
		<windowHeight>10600.0</windowHeight>
		<gapWidth>1140.0</gapWidth>
		<gapHeight>0.0</gapHeight>
		<horizontalPitch>99.99</horizontalPitch>
		<verticalPitch>90.08</verticalPitch>
		<topLeftLinear>14863.75</topLeftLinear>
		<topLeftY>-3551.25</topLeftY>
		<numHorizontalWindows>3</numHorizontalWindows>
		<triangular>1</triangular>
	</chip>
	<chip name="2018-Norcada-Xavier-Carolin">
		<chipWidth>31000</chipWidth>
		<chipHeight>10700</chipHeight>
		<windowWidth>880.0</windowWidth>
		<windowHeight>1740.0</windowHeight>
		<gapWidth>620.0</gapWidth>
		<gapHeight>500.0</gapHeight>
		<horizontalPitch>59.99</horizontalPitch>
		<verticalPitch>52.16</verticalPitch>
		<topLeftLinear>5699.4</topLeftLinear>
		<topLeftY>-3968.015625</topLeftY>
		<numHorizontalWindows>21</numHorizontalWindows>
		<triangular>1</triangular>
	</chip>
	<chip name="2018-Norcada-Hack">
		<chipWidth>31000</chipWidth>
		<chipHeight>10700</chipHeight>
		<windowWidth>880.0</windowWidth>
		<windowHeight>1740.0</windowHeight>
		<gapWidth>620.0</gapWidth>
		<gapHeight>628.0</gapHeight>
		<horizontalPitch>60.0</horizontalPitch>
		<verticalPitch>52.08</verticalPitch>
		<topLeftLinear>4762.6</topLeftLinear>
		<topLeftY>-5012.75</topLeftY>
		<numHorizontalWindows>21</numHorizontalWindows>
		<triangular>1</triangular>
	</chip>
	<chip name="2018-Miriam-Meng-Chips-3-Windows">
		<chipWidth>32350</chipWidth>
		<chipHeight>10300</chipHeight>
		<windowWidth>9980.0</windowWidth>
		<windowHeight>10300.0</windowHeight>
		<gapWidth>1200.0</gapWidth>
		<gapHeight>0.0</gapHeight>
		<horizontalPitch>100.0</horizontalPitch>
		<verticalPitch>89.85</verticalPitch>
		<topLeftLinear>9525.65</topLeftLinear>
		<topLeftY>-3877.65625</topLeftY>
		<numHorizontalWindows>3</numHorizontalWindows>
		<triangular>1</triangular>
	</chip>
	<chip name="2018-Miriam-Meng-Chips-24-Windows">
		<chipWidth>32800</chipWidth>
		<chipHeight>9720</chipHeight>
		<windowWidth>4400.0</windowWidth>
		<windowHeight>2000.0</windowHeight>
		<gapWidth>1280.0</gapWidth>
		<gapHeight>573.3</gapHeight>
		<horizontalPitch>159.3</horizontalPitch>
		<verticalPitch>119.6</verticalPitch>
		<topLeftLinear>9577.5</topLeftLinear>
		<topLeftY>-3761.015625</topLeftY>
		<numHorizontalWindows>6</numHorizontalWindows>
		<triangular>1</triangular>
	</chip>
	<chip name="2018-ESRF-simple">
		<chipWidth>32000</chipWidth>
		<chipHeight>10000</chipHeight>
		<windowWidth>32000.0</windowWidth>
		<windowHeight>10000.0</windowHeight>
		<gapWidth>0.0</gapWidth>
		<gapHeight>0.0</gapHeight>
		<horizontalPitch>10.0</horizontalPitch>
		<verticalPitch>5.0</verticalPitch>
		<topLeftLinear>7857.5</topLeftLinear>
		<topLeftY>-4700.0</topLeftY>
		<numHorizontalWindows>1</numHorizontalWindows>
		<triangular>1</triangular>
	</chip>
	<chip name="2018-Miriam-Meng-Chips-50um">
		<chipWidth>31800</chipWidth>
		<chipHeight>9080</chipHeight>
		<windowWidth>4080.0</windowWidth>
		<windowHeight>2000.0</windowHeight>
		<gapWidth>1280.0</gapWidth>
		<gapHeight>360.0</gapHeight>
		<horizontalPitch>49.987</horizontalPitch>
		<verticalPitch>43.34</verticalPitch>
		<topLeftLinear>5847.3</topLeftLinear>
		<topLeftY>-5085.25</topLeftY>
		<numHorizontalWindows>6</numHorizontalWindows>
		<triangular>1</triangular>
	</chip>
	<chip name="2018-Finnlitho">
		<chipWidth>28557</chipWidth>
		<chipHeight>7900</chipHeight>
		<windowWidth>1154.0</windowWidth>
		<windowHeight>1500.0</windowHeight>
		<gapWidth>400.0</gapWidth>
		<gapHeight>100.0</gapHeight>
		<horizontalPitch>50.0</horizontalPitch>
		<verticalPitch>43.42</verticalPitch>
		<topLeftLinear>14907.5</topLeftLinear>
		<topLeftY>-3442.5</topLeftY>
		<numHorizontalWindows>18</numHorizontalWindows>
		<triangular>1</triangular>
	</chip>
	<chip name="2018-Rectangular">
		<chipWidth>33250</chipWidth>
		<chipHeight>10500</chipHeight>
		<windowWidth>33250.0</windowWidth>
		<windowHeight>10500.0</windowHeight>
		<gapWidth>0.0</gapWidth>
		<gapHeight>0.0</gapHeight>
		<horizontalPitch>50.0</horizontalPitch>
		<verticalPitch>43.23</verticalPitch>
		<topLeftLinear>1270.0</topLeftLinear>
		<topLeftY>-4565.0</topLeftY>
		<numHorizontalWindows>1</numHorizontalWindows>
		<triangular>0</triangular>
	</chip>
	<chip name="2018-Membrane-25um">
		<chipWidth>33360</chipWidth>
		<chipHeight>9800</chipHeight>
		<windowWidth>4226.0</windowWidth>
		<windowHeight>4100.0</windowHeight>
		<gapWidth>1600.0</gapWidth>
		<gapHeight>1600.0</gapHeight>
		<horizontalPitch>200.0</horizontalPitch>
		<verticalPitch>120.0</verticalPitch>
		<topLeftLinear>6900.0</topLeftLinear>
		<topLeftY>-5000.0</topLeftY>
		<numHorizontalWindows>6</numHorizontalWindows>
		<triangular>1</triangular>
	</chip>
	<chip name="2018-MM-Chips-24-Windows-pitch300">
		<chipWidth>32800</chipWidth>
		<chipHeight>9720</chipHeight>
		<windowWidth>3470.0</windowWidth>
		<windowHeight>2000.0</windowHeight>
		<gapWidth>2400.0</gapWidth>
		<gapHeight>573.3</gapHeight>
		<horizontalPitch>300</horizontalPitch>
		<verticalPitch>300</verticalPitch>
		<topLeftLinear>3600.0</topLeftLinear>
		<topLeftY>-4870.0</topLeftY>
		<numHorizontalWindows>6</numHorizontalWindows>
		<triangular>1</triangular>
	</chip>
</chips>